[{"type":"User","firstName":"Tommy","lastName":"Marley","email":"Marley@mail.com"},{"type":"Student","firstName":"Bob","lastName":"Nossom","email":"Bob@mail.com","cource":4,"groupe":"ИВ2-22"},{"type":"Student","firstName":"Alice","lastName":"Berry","email":"Berry@mail.com","cource":3,"groupe":"ИВ2-21"},{"type":"Teacher","firstName":"Mary","lastName":"Lock","email":"Lock@mail.com","subjects":["русский","литература"]},{"type":"Teacher","firstName":"Josh","lastName":"Washington","email":"Washington@mail.com","subjects":["английский"]},{"type":"Manager","firstName":"Lenny","lastName":"Lockster","email":"Lockster@mail.com","position":"завуч","jobDuties":["организация учебного процесса","выполнение учебных программ"]},{"type":"Manager","firstName":"Helen","lastName":"Marine","email":"Marine@mail.com","position":"директор","jobDuties":["организация образовательной (учебно-воспитательной) работы"," создание режима соблюдения норм и правил"]}]